openfaces/OpenFaces.py
openfaces/__init__.py
openfaces/attributes/Age.py
openfaces/attributes/Emotion.py
openfaces/attributes/Gender.py
openfaces/attributes/Race.py
openfaces/attributes/__init__.py
openfaces/faces/DeepFace.py
openfaces/faces/DeepID.py
openfaces/faces/DlibResNet.py
openfaces/faces/FaceNet.py
openfaces/faces/OpenFace.py
openfaces/faces/VGGFace.py
openfaces/faces/__init__.py
openfaces/libs/__init__.py
openfaces/libs/distance.py
openfaces/libs/functions.py
open_faces-0.1.4.dist-info/METADATA
open_faces-0.1.4.dist-info/WHEEL
open_faces-0.1.4.dist-info/top_level.txt
open_faces-0.1.4.dist-info/zip-safe
open_faces-0.1.4.dist-info/RECORD
