Metadata-Version: 2.1
Name: open-faces
Version: 0.1.4
Summary: Open Faces Toolkit
Home-page: https://github.com/CachCheng/OpenFaces
Author: CachCheng
Author-email: tkggpdc2007@163.com
License: Apache-2.0
Platform: UNKNOWN
Requires-Dist: numpy
Requires-Dist: pandas
Requires-Dist: gdown
Requires-Dist: opencv-python
Requires-Dist: flask
Requires-Dist: Pillow
Requires-Dist: dlib
Requires-Dist: keras
Requires-Dist: tensorflow
